review/__init__.py
review/app.py
re_view-0.15.1.dist-info/LICENSE
re_view-0.15.1.dist-info/METADATA
re_view-0.15.1.dist-info/WHEEL
re_view-0.15.1.dist-info/entry_points.txt
re_view-0.15.1.dist-info/top_level.txt
re_view-0.15.1.dist-info/RECORD
