Metadata-Version: 2.1
Name: re-view
Version: 0.15.1
Summary: Terminal based regex visualization tool and debugger.
Home-page: https://github.com/wqferr/re-view
Author: William Quelho Ferreira
Author-email: wqferr@gmail.com
License: GPLv3
Keywords: regex visualization tool debug
Platform: UNKNOWN
Classifier: Development Status :: 3 - Alpha
Classifier: Topic :: Utilities
Classifier: Intended Audience :: Developers
Classifier: License :: OSI Approved :: GNU General Public License v3 (GPLv3)
Classifier: Programming Language :: Python :: 3 :: Only
Requires-Dist: blessed (>=1.16)
Requires-Dist: lorem (>=0.1.1)
